splitsql/__init__.py
splitsql/main.py
splitsql-0.0.6.dist-info/LICENSE.txt
splitsql-0.0.6.dist-info/METADATA
splitsql-0.0.6.dist-info/WHEEL
splitsql-0.0.6.dist-info/entry_points.txt
splitsql-0.0.6.dist-info/top_level.txt
splitsql-0.0.6.dist-info/RECORD
