Metadata-Version: 2.1
Name: splitsql
Version: 0.0.6
Summary: It will split all the table and views of a schema in a file, into its respective files
Home-page: https://github.com/balagdivya/splitsql
Author: Divya Goteti
Author-email: balagdivya@gmail.com
License: UNKNOWN
Platform: UNKNOWN
Classifier: Programming Language :: Python :: 3
Classifier: License :: OSI Approved :: MIT License
Classifier: Operating System :: OS Independent
Requires-Dist: argparse
